lsst/alert/packet/__init__.py
lsst/alert/packet/io.py
lsst/alert/packet/schema.py
lsst/alert/packet/schemaRegistry.py
lsst/alert/packet/simulate.py
lsst/alert/packet/bin/simulateAlerts.py
lsst/alert/packet/bin/validateAvroRoundTrip.py
lsst/alert/packet/schema/latest.txt
lsst/alert/packet/schema/3/0/lsst.v3_0.alert.avsc
lsst/alert/packet/schema/3/0/lsst.v3_0.diaForcedSource.avsc
lsst/alert/packet/schema/3/0/lsst.v3_0.diaNondetectionLimit.avsc
lsst/alert/packet/schema/3/0/lsst.v3_0.diaObject.avsc
lsst/alert/packet/schema/3/0/lsst.v3_0.diaSource.avsc
lsst/alert/packet/schema/3/0/lsst.v3_0.ssObject.avsc
lsst/alert/packet/schema/3/0/sample_data/alert.json
lsst/alert/packet/schema/3/0/sample_data/fakeAlert.avro
lsst/alert/packet/schema/3/0/sample_data/generate.py
lsst/alert/packet/schema/examples/simple.avsc
lsst/alert/packet/schema/examples/simplest.avsc
lsst/alert/packet/schema/examples/sample_data/simple.json
lsst/alert/packet/schema/examples/sample_data/simplest.json
lsst_alert_packet-0.2.1.dist-info/LICENSE
lsst_alert_packet-0.2.1.dist-info/METADATA
lsst_alert_packet-0.2.1.dist-info/WHEEL
lsst_alert_packet-0.2.1.dist-info/entry_points.txt
lsst_alert_packet-0.2.1.dist-info/top_level.txt
lsst_alert_packet-0.2.1.dist-info/RECORD
